syft_datasets/__init__.py
syft_datasets/config.py
syft_datasets/dataset.py
syft_datasets/dataset_manager.py
syft_datasets/file_utils.py
syft_datasets/types.py
syft_datasets/url.py
syft_dataset-0.1.5.dist-info/METADATA
syft_dataset-0.1.5.dist-info/WHEEL
syft_dataset-0.1.5.dist-info/RECORD
