Metadata-Version: 2.4
Name: syft-dataset
Version: 0.1.5
Summary: Syft Datasets
Author-email: OpenMined <info@openmined.org>
License: Apache-2.0
Requires-Python: >=3.12
Requires-Dist: pyyaml>=6.0.3
Requires-Dist: syft-notebook-ui
